README
setup.py
firefogg/__init__.py
firefogg/form.py
python_firefogg.egg-info/PKG-INFO
python_firefogg.egg-info/SOURCES.txt
python_firefogg.egg-info/dependency_links.txt
python_firefogg.egg-info/top_level.txt