Metadata-Version: 1.0
Name: python-firefogg
Version: 1.0.8
Summary: python-firefogg - video encoding and uploading for python
